README.md
setup.py
gallilama_helloworld.egg-info/PKG-INFO
gallilama_helloworld.egg-info/SOURCES.txt
gallilama_helloworld.egg-info/dependency_links.txt
gallilama_helloworld.egg-info/not-zip-safe
gallilama_helloworld.egg-info/top_level.txt
hello/__init__.py