Metadata-Version: 1.0
Name: gallilama-helloworld
Version: 1.3.0
Summary: Hello world to test Gitlab PyPi process
Home-page: UNKNOWN
Author: gallilama
Author-email: gallilama@gmail.com
License: MIT
Platform: UNKNOWN
